importanize/__init__.py
importanize/__main__.py
importanize/formatters.py
importanize/groups.py
importanize/mixin.py
importanize/parser.py
importanize/statements.py
importanize/utils.py
importanize-0.7.0.dist-info/DESCRIPTION.rst
importanize-0.7.0.dist-info/METADATA
importanize-0.7.0.dist-info/RECORD
importanize-0.7.0.dist-info/WHEEL
importanize-0.7.0.dist-info/entry_points.txt
importanize-0.7.0.dist-info/metadata.json
importanize-0.7.0.dist-info/top_level.txt
tests/__init__.py
tests/test_formatters.py
tests/test_groups.py
tests/test_main.py
tests/test_mixins.py
tests/test_parser.py
tests/test_statements.py
tests/test_utils.py
