Metadata-Version: 2.0
Name: importanize
Version: 0.7.0
Summary: Utility for organizing Python imports using PEP8 or custom rules
Home-page: https://github.com/miki725/importanize
Author: Miroslav Shubernetskiy
Author-email: UNKNOWN
License: MIT
Keywords: importanize
Platform: UNKNOWN
Classifier: Intended Audience :: Developers
Classifier: Natural Language :: English
Classifier: License :: OSI Approved :: MIT License
Classifier: Programming Language :: Python
Classifier: Programming Language :: Python :: 2.7
Classifier: Programming Language :: Python :: 3
Classifier: Programming Language :: Python :: 3.4
Classifier: Development Status :: 2 - Pre-Alpha
Requires-Dist: pathlib2
Requires-Dist: setuptools
Requires-Dist: six (>=1.9)
